Workbook

Sheet Read Me
A1: HAWAIʻI 2026 | Adventure Trip Budget & Tracker
A2: Five travelers maximum • Sept 20–27, 2026 • Hawaiʻi Island + Kauaʻi • research/planning version
A4: Editable planning controls | D4: How to use this workbook
A5: Travelers | B5: 5 | D5: 1. Replace yellow assumptions and quote cells only.
A6: Maximum target / person | B6: 2500 | D6: 2. Use Budget Dashboard for the live per-person and group estimate.
A7: Main airfare placeholder / person | B7: 650 | D7: 3. Use Itemized Budget for every planned expense and mark optional items.
A8: KOA→LIH inter-island flight / person | B8: 120 | D8: 4. Use Daily Plan for the hour-by-hour schedule.
A9: Lodging / room-night | B9: 240 | D9: 5. Lodging and Transport hold actual quote/booking details.
A10: Nights | B10: 7 | D10: 6. Sources keeps official planning links separate from estimates.
A11: Food / person | B11: 300 | D11: 7. September weather, trail closures, road conditions and Kīlauea activity must be rechecked immediately before travel.
A12: Activities / person | B12: 260
A13: Rental cars + fuel / person | B13: 160 | D13: Route | E13: CMH → KOA → Hawaiʻi Island → LIH → Kauaʻi → CMH
A14: Misc / contingency / person | B14: 100 | D14: Dates | E14: Sun Sep 20 through Sun Sep 27, 2026
D15: Trip style | E15: Early mornings, substantial hiking, scenery-first, two islands
D17: Important live-status links
D18: USGS Kīlauea updates | E18: https://www.usgs.gov/volcanoes/kilauea/volcano-updates
D19: NPS Hawaiʻi Volcanoes | E19: https://www.nps.gov/havo/index.htm
D20: NPS eruption viewing | E20: https://www.nps.gov/havo/planyourvisit/eruption-viewing.htm
D21: Hawaiʻi Tropical Botanical Garden | E21: https://htbg.com/plan-your-visit/
D22: GoHawaii Kauaʻi / Nā Pali | E22: https://www.gohawaii.com/islands/kauai/regions/north-shore/napali-coast

Sheet Budget Dashboard
A1: Budget Dashboard
A2: Live-style planning dashboard for 4–5 travelers. Replace yellow assumptions with actual quotes as you book.
A5: Scenario / metric | B5: Per person | C5: Group total | D5: Against $2,500 target | E5: Notes
A6: Planning estimate | B6: =SUM('Itemized Budget'!H5:H31) | C6: =B6*'Read Me'!$B$5 | D6: =B6-'Read Me'!$B$6 | E6: Uses current planning assumptions
A7: Core trip excluding contingency | B7: =SUM('Itemized Budget'!H5:H29) | C7: =B7*'Read Me'!$B$5 | D7: =B7-'Read Me'!$B$6
A8: Target | B8: ='Read Me'!$B$6 | C8: =B8*'Read Me'!$B$5 | D8: =0 | E8: User-editable target
A9: Current actuals entered | B9: =SUM('Itemized Budget'!I5:I31) | C9: =B9*'Read Me'!$B$5 | D9: =B9-'Read Me'!$B$6 | E9: Only counts filled Actual cells
A12: Cost category | B12: Per person | C12: Group total
A13: Main airfare | B13: 650 | C13: =B13*'Read Me'!$B$5
A14: Inter-island flight | B14: 120 | C14: =B14*'Read Me'!$B$5
A15: Lodging | B15: 635 | C15: =B15*'Read Me'!$B$5
A16: Food | B16: 315 | C16: =B16*'Read Me'!$B$5
A17: Activities / admissions | B17: 250 | C17: =B17*'Read Me'!$B$5
A18: Cars / fuel / parking | B18: 70 | C18: =B18*'Read Me'!$B$5
A19: Misc / contingency | B19: 100 | C19: =B19*'Read Me'!$B$5

Sheet Itemized Budget
A1: Itemized Budget
A2: Every major trip cost, with editable estimate and actual columns. Prices are planning estimates until replaced with live quotes.
A4: Date | B4: Day | C4: Island | D4: Location | E4: Category | F4: Item | G4: Required? | H4: Est. $/person | I4: Actual $/person | J4: Group Est. | K4: Notes / booking trigger
A5: 2026-09-20 | B5: Day 1 | C5: Travel | D5: CMH→KOA | E5: Airfare | F5: Main round-trip/open-jaw airfare | G5: Yes | H5: 650 | J5: =H5*'Read Me'!$B$5 | K5: Replace with chosen flight quote
A6: 2026-09-20 | B6: Day 1 | C6: Hawaiʻi Island | D6: KOA | E6: Transport | F6: Rental car + first-day allocation | G6: Yes | H6: 35 | J6: =H6*'Read Me'!$B$5 | K6: Two rental cars may be useful for 5 travelers
A7: 2026-09-20 | B7: Day 1 | C7: Hawaiʻi Island | D7: Kona | E7: Lodging | F7: Night 1 lodging | G7: Yes | H7: 120 | J7: =H7*'Read Me'!$B$5 | K7: Depends on room configuration
A8: 2026-09-20 | B8: Day 1 | C8: Hawaiʻi Island | D8: Kona | E8: Food | F8: Food + groceries | G8: Yes | H8: 45 | J8: =H8*'Read Me'!$B$5
A9: 2026-09-21 | B9: Day 2 | C9: Hawaiʻi Island | D9: Volcanoes NP | E9: Park | F9: Park / parking / access allowance | G9: Yes | H9: 10 | J9: =H9*'Read Me'!$B$5 | K9: Check current park conditions
A10: 2026-09-21 | B10: Day 2 | C10: Hawaiʻi Island | D10: Kīlauea Iki | E10: Activity | F10: Kīlauea Iki hike | G10: Yes | H10: 0 | J10: =H10*'Read Me'!$B$5 | K10: Trail conditions may change
A11: 2026-09-21 | B11: Day 2 | C11: Hawaiʻi Island | D11: Volcano | E11: Lodging | F11: Night 2 lodging | G11: Yes | H11: 75 | J11: =H11*'Read Me'!$B$5 | K11: Volcano Village preferred
A12: 2026-09-22 | B12: Day 3 | C12: Hawaiʻi Island | D12: Hilo | E12: Activity | F12: Hawaiʻi Tropical Botanical Garden | G12: Yes | H12: 35 | J12: =H12*'Read Me'!$B$5 | K12: Current adult admission benchmark
A13: 2026-09-22 | B13: Day 3 | C13: Hawaiʻi Island | D13: Akaka Falls | E13: Activity | F13: Akaka Falls / parking allowance | G13: Yes | H13: 15 | J13: =H13*'Read Me'!$B$5
A14: 2026-09-22 | B14: Day 3 | C14: Hawaiʻi Island | D14: Hilo | E14: Lodging | F14: Night 3 lodging | G14: Yes | H14: 75 | J14: =H14*'Read Me'!$B$5
A15: 2026-09-22 | B15: Day 3 | C15: Hawaiʻi Island | D15: Hilo | E15: Food | F15: Food | G15: Yes | H15: 45 | J15: =H15*'Read Me'!$B$5
A16: 2026-09-23 | B16: Day 4 | C16: Hawaiʻi Island | D16: Mauna Kea | E16: Activity | F16: Mauna Kea sunset / stargazing | G16: Yes | H16: 0 | J16: =H16*'Read Me'!$B$5 | K16: Check summit access, weather and altitude guidance
A17: 2026-09-23 | B17: Day 4 | C17: Hawaiʻi Island | D17: Hilo | E17: Lodging | F17: Night 4 lodging | G17: Yes | H17: 75 | J17: =H17*'Read Me'!$B$5
A18: 2026-09-23 | B18: Day 4 | C18: Hawaiʻi Island | D18: Hilo | E18: Food | F18: Food | G18: Yes | H18: 45 | J18: =H18*'Read Me'!$B$5
A19: 2026-09-24 | B19: Day 5 | C19: Air | D19: KOA→LIH | E19: Airfare | F19: Inter-island flight | G19: Yes | H19: 120 | J19: =H19*'Read Me'!$B$5 | K19: Book as separate short-haul leg
A20: 2026-09-24 | B20: Day 5 | C20: Kauaʻi | D20: LIH | E20: Transport | F20: Kauaʻi rental car allocation | G20: Yes | H20: 35 | J20: =H20*'Read Me'!$B$5
A21: 2026-09-24 | B21: Day 5 | C21: Kauaʻi | D21: Hanalei | E21: Lodging | F21: Night 5 lodging | G21: Yes | H21: 120 | J21: =H21*'Read Me'!$B$5
A22: 2026-09-24 | B22: Day 5 | C22: Kauaʻi | D22: Hanalei | E22: Food | F22: Food | G22: Yes | H22: 45 | J22: =H22*'Read Me'!$B$5
A23: 2026-09-25 | B23: Day 6 | C23: Kauaʻi | D23: Waimea Canyon | E23: Activity | F23: Waimea Canyon / Kōkeʻe hiking | G23: Yes | H23: 10 | J23: =H23*'Read Me'!$B$5
A24: 2026-09-25 | B24: Day 6 | C24: Kauaʻi | D24: Kapaʻa/Hanalei | E24: Lodging | F24: Night 6 lodging | G24: Yes | H24: 120 | J24: =H24*'Read Me'!$B$5
A25: 2026-09-25 | B25: Day 6 | C25: Kauaʻi | D25: Kauaʻi | E25: Food | F25: Food | G25: Yes | H25: 45 | J25: =H25*'Read Me'!$B$5
A26: 2026-09-26 | B26: Day 7 | C26: Kauaʻi | D26: Nā Pali Coast | E26: Activity | F26: Nā Pali Coast boat tour | G26: Yes | H26: 180 | J26: =H26*'Read Me'!$B$5 | K26: Reserve early; operator/weather dependent
A27: 2026-09-26 | B27: Day 7 | C27: Kauaʻi | D27: Poʻipū | E27: Lodging | F27: Night 7 lodging | G27: Yes | H27: 120 | J27: =H27*'Read Me'!$B$5
A28: 2026-09-26 | B28: Day 7 | C28: Kauaʻi | D28: Kauaʻi | E28: Food | F28: Food | G28: Yes | H28: 45 | J28: =H28*'Read Me'!$B$5
A29: 2026-09-27 | B29: Return | C29: Kauaʻi→Ohio | D29: LIH→CMH | E29: Airfare | F29: Return flight | G29: Yes | H29: 0 | J29: =H29*'Read Me'!$B$5 | K29: Included in main airfare placeholder
A30: Trip | B30: All | C30: All | D30: All | E30: Budget | F30: Contingency / misc. | G30: Optional | H30: 100 | J30: =H30*'Read Me'!$B$5 | K30: Emergency/parking/small purchases

Sheet Daily Plan
A1: Daily Plan
A2: Hour-by-hour schedule for Sept. 20–27. The major scenery moments are deliberately given large blocks of time.
A4: Date | B4: Day | C4: Overnight / base | D4: Time | E4: Primary plan | F4: Location | G4: Transport | H4: Est. $/person | I4: Booking / safety checkpoint
A5: 2026-09-20 | B5: Day 1 | C5: Kona | D5: 7:00 AM | E5: Depart CMH | F5: CMH | G5: Flight | H5: 650 | I5: Confirm bags and connection
A6: 2026-09-20 | B6: Day 1 | C6: Kona | D6: 12:30 PM | E6: Arrive, rental car, groceries | F6: KOA / Kona | G6: Rental car | H6: 35
A7: 2026-09-20 | B7: Day 1 | C7: Kona | D7: 4:00 PM | E7: Beach / explore | F7: Kona Coast | G7: Car | H7: 10
A8: 2026-09-20 | B8: Day 1 | C8: Kona | D8: 6:30 PM | E8: Sunset dinner | F8: Kona | G8: Walk/car | H8: 45
A9: 2026-09-21 | B9: Day 2 | C9: Volcano | D9: 5:00 AM | E9: Early drive + breakfast | F9: Kona → Volcano | G9: Car | H9: 20 | I9: Check NPS/USGS conditions
A10: 2026-09-21 | B10: Day 2 | C10: Volcano | D10: 7:30 AM | E10: Kīlauea Iki crater hike | F10: Hawaiʻi Volcanoes NP | G10: Hike | H10: 0 | I10: Check trail status
A11: 2026-09-21 | B11: Day 2 | C11: Volcano | D11: 11:30 AM | E11: Thurston Lava Tube | F11: Nāhuku | G11: Walk | H11: 0
A12: 2026-09-21 | B12: Day 2 | C12: Volcano | D12: 1:30 PM | E12: Chain of Craters Road + lava fields + coast | F12: Hawaiʻi Volcanoes NP | G12: Car | H12: 10 | I12: Do not cross closures/barriers
A13: 2026-09-21 | B13: Day 2 | C13: Volcano | D13: 8:00 PM | E13: Eruption viewing if conditions allow | F13: Kīlauea area | G13: Car | H13: 0 | I13: Activity is not guaranteed
A14: 2026-09-22 | B14: Day 3 | C14: Hilo | D14: 9:00 AM | E14: Tropical Botanical Garden | F14: Onomea Bay | G14: Car | H14: 35 | I14: Allow 90–120 minutes
A15: 2026-09-22 | B15: Day 3 | C15: Hilo | D15: 11:30 AM | E15: Hamakua Coast scenic drive | F15: Hamakua Coast | G15: Car | H15: 10
A16: 2026-09-22 | B16: Day 3 | C16: Hilo | D16: 2:00 PM | E16: Akaka Falls rainforest hike | F16: Akaka Falls | G16: Hike | H16: 15 | I16: Check current access
A17: 2026-09-22 | B17: Day 3 | C17: Hilo | D17: 7:00 PM | E17: Dinner + sleep | F17: Hilo | G17: Car/walk | H17: 45
A18: 2026-09-23 | B18: Day 4 | C18: Hilo | D18: 9:00 AM | E18: Drive / scenic stops | F18: Saddle Road | G18: Car | H18: 10 | I18: Acclimatize before high elevation
A19: 2026-09-23 | B19: Day 4 | C19: Hilo | D19: 3:00 PM | E19: Head toward Mauna Kea | F19: Mauna Kea access area | G19: Car | H19: 0 | I19: Check weather/access rules
A20: 2026-09-23 | B20: Day 4 | C20: Hilo | D20: 5:30 PM | E20: Sunset above the clouds | F20: Mauna Kea | G20: Scenery | H20: 0 | I20: Altitude/weather dependent
A21: 2026-09-23 | B21: Day 4 | C21: Hilo | D21: 7:00 PM | E21: Stargazing / astronomy | F21: Mauna Kea | G21: Scenery | H21: 0 | I21: Follow current access rules
A22: 2026-09-24 | B22: Day 5 | C22: Hanalei | D22: 6:00 AM | E22: Airport + return rental | F22: KOA | G22: Car/flight | H22: 0 | I22: Allow airport time
A23: 2026-09-24 | B23: Day 5 | C23: Hanalei | D23: 8:00 AM | E23: Inter-island flight | F23: KOA → LIH | G23: Flight | H23: 120
A24: 2026-09-24 | B24: Day 5 | C24: Hanalei | D24: 1:00 PM | E24: North Shore drive + viewpoints | F24: Hanalei | G24: Car | H24: 10
A25: 2026-09-24 | B25: Day 5 | C25: Hanalei | D25: 3:00 PM | E25: Hanalei Bay | F25: Hanalei | G25: Walk | H25: 0 | I25: Ocean conditions matter
A26: 2026-09-25 | B26: Day 6 | C26: Hanalei | D26: 5:30 AM | E26: Drive to Waimea | F26: Hanalei → Waimea | G26: Car | H26: 20 | I26: Early start
A27: 2026-09-25 | B27: Day 6 | C27: Hanalei | D27: 7:30 AM | E27: Waimea Canyon viewpoints | F27: Waimea Canyon | G27: Walk | H27: 0 | I27: Weather can change quickly
A28: 2026-09-25 | B28: Day 6 | C28: Hanalei | D28: 10:00 AM | E28: Long Kōkeʻe hike | F28: Kōkeʻe State Park | G28: Hike | H28: 10 | I28: Choose trail based on conditions
A29: 2026-09-25 | B29: Day 6 | C29: Hanalei | D29: 3:30 PM | E29: West-side scenic stops | F29: West Kauaʻi | G29: Car | H29: 0
A30: 2026-09-26 | B30: Day 7 | C30: Poʻipū | D30: 8:00 AM | E30: Nā Pali Coast boat tour | F30: Nā Pali Coast | G30: Boat | H30: 180 | I30: Reserve; weather/operator dependent
A31: 2026-09-26 | B31: Day 7 | C31: Poʻipū | D31: 2:00 PM | E31: Poʻipū beach / relax | F31: Poʻipū | G31: Car/walk | H31: 0
A32: 2026-09-26 | B32: Day 7 | C32: Poʻipū | D32: 5:30 PM | E32: Final Hawaiian sunset | F32: South Shore | G32: Walk | H32: 0
A33: 2026-09-27 | B33: Return | C33: Home | D33: 7:00 AM | E33: LIH → CMH | F33: Līhuʻe | G33: Flight | H33: 0 | I33: Arrive airport with airline-recommended buffer

Sheet Lodging
A1: Lodging Shortlist
A2: For 4–5 adults, prioritize a whole multi-bed room/condo where allowed. Prices below are planning bands, not live quotes.
A4: Area | B4: Role | C4: Planning band / room-night | D4: Nights | E4: Estimated pp share | F4: Why it fits | G4: Booking trigger | H4: Official / search link
A5: Kona | B5: Arrival base | C5: $180–300 | D5: 1 | E5: 120 | F5: Convenient first-night base | G5: Quote exact Sept 20 | H5: https://www.gohawaii.com/islands/hawaii-big-island
A6: Volcano Village | B6: Volcano night | C6: $150–240 | D6: 1 | E6: 75 | F6: Minimizes post-park driving | G6: Quote Sept 21 | H6: https://www.nps.gov/havo/planyourvisit/where-to-stay.htm
A7: Hilo | B7: Rainforest / Mauna Kea base | C7: $150–240 | D7: 2 | E7: 75 | F7: Good for Hilo + Mauna Kea | G7: Quote Sept 22–23 | H7: https://www.gohawaii.com/islands/hawaii-big-island/regions/hilo
A8: Hanalei / Princeville | B8: North Shore | C8: $220–360 | D8: 2 | E8: 120 | F8: Excellent scenery + North Shore access | G8: Quote Sept 24–25 | H8: https://www.gohawaii.com/islands/kauai/regions/north-shore
A9: Poʻipū / Līhuʻe | B9: Final night | C9: $220–360 | D9: 1 | E9: 120 | F9: Convenient for south shore / airport | G9: Quote Sept 26 | H9: https://www.gohawaii.com/islands/kauai/regions/south-shore

Sheet Transport
A1: Transport Plan
A2: Open-jaw flights and two rental cars are the planning baseline; confirm exact fares and vehicle terms.
A4: Leg | B4: Recommended option | C4: Planning $ pp | D4: Duration / timing | E4: Reliability / safety note | F4: Booking trigger | G4: Official link
A5: CMH → KOA | B5: Main airline itinerary | C5: 650 | D5: Connection dependent | E5: Compare total fare + bags, not headline fare | F5: Book after dates confirmed | G5: https://www.aa.com/
A6: KOA → LIH | B6: Inter-island flight | C6: 120 | D6: ~1 hr nonstop when available | E6: Build airport buffer; fares vary | F6: Book with main itinerary | G6: https://www.hawaiianairlines.com/
A7: KOA rental | B7: Compact/SUV allocation | C7: 70 | D7: Days 1–4 | E7: Compare 2 cars vs one larger vehicle for 5 | F7: Quote exact dates | G7: https://www.enterprise.com/
A8: LIH rental | B8: Compact/SUV allocation | C8: 90 | D8: Days 5–7 | E8: Compare one 5-seat SUV vs two cars | F8: Quote exact dates | G8: https://www.enterprise.com/
A9: LIH → CMH | B9: Return flight | C9: 0 | D9: Connection dependent | E9: Main airfare placeholder assumes round-trip/open-jaw total | F9: Book with outbound | G9: https://www.aa.com/

Sheet Options Comparison
A1: Trip Options Comparison
A2: The chosen plan is Big Island + Kauaʻi. This sheet makes the core decision auditable.
A4: Option | B4: Days | C4: Main scenery | D4: Travel complexity | E4: Planning cost / pp | F4: Recommendation | G4: Why
A5: Big Island + Kauaʻi | B5: 7 nights | C5: Volcanoes, rainforest, Mauna Kea, canyon, Nā Pali | D5: Medium | E5: $1,800–$2,500 | F5: SELECTED | G5: Maximum scenery variety without adding a third island
A6: Big Island only | B6: 7 nights | C6: Volcanoes, waterfalls, Mauna Kea | D6: Low | E6: $1,500–$2,200 | F6: Backup | G6: Less airport friction but misses Nā Pali / Waimea
A7: Kauaʻi only | B7: 7 nights | C7: Nā Pali, Waimea, rainforest | D7: Low | E7: $1,500–$2,300 | F7: Backup | G7: Best concentrated scenery; misses volcano / Mauna Kea

Sheet Booking Checklist
A1: Booking & Verification Checklist
A2: Replace estimates with confirmed quotes and save the evidence in one place.
A4: Priority | B4: Deadline | C4: Action | D4: Owner | E4: Status | F4: Evidence to save | G4: Budget update | H4: Link / note
A5: Critical | B5: Now | C5: Confirm 4–5 travelers and exact Sept 20–27 dates | D5: Group | E5: Not started | F5: Final group count | G5: Update Read Me B5
A6: Critical | B6: Now | C6: Compare CMH→KOA and LIH→CMH open-jaw fares | D6: Traveler 1 | E6: Not started | F6: Flight numbers, times, bags, final total | G6: Update Itemized Budget
A7: Critical | B7: After flights | C7: Quote lodging on Big Island and Kauaʻi | D7: Traveler 2 | E7: Not started | F7: Cancellation terms + taxes | G7: Update Lodging
A8: High | B8: After lodging | C8: Book inter-island KOA→LIH | D8: Traveler 1 | E8: Not started | F8: Ticket + baggage rules | G8: Update Itemized Budget
A9: High | B9: After lodging | C9: Reserve rental cars | D9: Traveler 3 | E9: Not started | F9: Rental agreement + insurance terms | G9: Update Transport
A10: High | B10: Before Day 2 | C10: Check NPS park/trail closures and USGS Kīlauea update | D10: Traveler 4 | E10: Not started | F10: Screenshot / link | G10: No cost
A11: High | B11: Before Day 4 | C11: Check Mauna Kea weather/access/altitude guidance | D11: Traveler 4 | E11: Not started | F11: Current official guidance | G11: No cost
A12: High | B12: Before Day 7 | C12: Book Nā Pali Coast boat tour | D12: Traveler 2 | E12: Not started | F12: Confirmation + cancellation weather policy | G12: Update Itemized Budget
A13: Medium | B13: Week before | C13: Download offline maps + share itinerary | D13: All | E13: Not started | F13: Offline map / shared doc | G13: No cost
A14: Medium | B14: Week before | C14: Reconfirm every major trail, road and attraction | D14: All | E14: Not started | F14: Current status pages | G14: Update notes

Sheet Sources
A1: Source Register
A2: Official sources prioritized for safety, schedules, park conditions and attraction details.
A4: ID | B4: Title | C4: Publisher | D4: Type | E4: URL | F4: Use
A5: S01 | B5: Kīlauea Volcano Updates | C5: USGS | D5: Official | E5: https://www.usgs.gov/volcanoes/kilauea/volcano-updates | F5: Current eruption status
A6: S02 | B6: Hawaiʻi Volcanoes National Park | C6: NPS | D6: Official | E6: https://www.nps.gov/havo/index.htm | F6: Park conditions, hikes, closures
A7: S03 | B7: Eruption Viewing | C7: NPS | D7: Official | E7: https://www.nps.gov/havo/planyourvisit/eruption-viewing.htm | F7: Viewing rules / current activity
A8: S04 | B8: Hawaiʻi Tropical Botanical Garden | C8: HTBG | D8: Official | E8: https://htbg.com/plan-your-visit/ | F8: Hours and admission
A9: S05 | B9: Kauaʻi / Nā Pali Coast | C9: GoHawaii | D9: Tourism authority | E9: https://www.gohawaii.com/islands/kauai/regions/north-shore/napali-coast | F9: Destination background
A10: S06 | B10: Mauna Kea Observatories | C10: MKSOA | D10: Official | E10: https://www.maunakeaobservatories.org/ | F10: Mauna Kea astronomy/access context
A11: S07 | B11: American Airlines | C11: American | D11: Airline | E11: https://www.aa.com/ | F11: Flight quote starting point
A12: S08 | B12: Hawaiian Airlines | C12: Hawaiian | D12: Airline | E12: https://www.hawaiianairlines.com/ | F12: Inter-island quote starting point
